pulumiverse_grafana/__init__.py
pulumiverse_grafana/_utilities.py
pulumiverse_grafana/provider.py
pulumiverse_grafana/pulumi-plugin.json
pulumiverse_grafana/py.typed
pulumiverse_grafana/alerting/__init__.py
pulumiverse_grafana/alerting/_inputs.py
pulumiverse_grafana/alerting/alert_enrichment.py
pulumiverse_grafana/alerting/alert_rule_v0_alpha1.py
pulumiverse_grafana/alerting/contact_point.py
pulumiverse_grafana/alerting/message_template.py
pulumiverse_grafana/alerting/mute_timing.py
pulumiverse_grafana/alerting/notification_policy.py
pulumiverse_grafana/alerting/outputs.py
pulumiverse_grafana/alerting/recording_rule_v0_alpha1.py
pulumiverse_grafana/alerting/rule_group.py
pulumiverse_grafana/assert_/__init__.py
pulumiverse_grafana/assert_/_inputs.py
pulumiverse_grafana/assert_/custom_model_rules.py
pulumiverse_grafana/assert_/log_config.py
pulumiverse_grafana/assert_/notification_alerts_config.py
pulumiverse_grafana/assert_/outputs.py
pulumiverse_grafana/assert_/suppressed_assertions_config.py
pulumiverse_grafana/assert_/thresholds.py
pulumiverse_grafana/cloud/__init__.py
pulumiverse_grafana/cloud/_inputs.py
pulumiverse_grafana/cloud/access_policy.py
pulumiverse_grafana/cloud/access_policy_rotating_token.py
pulumiverse_grafana/cloud/access_policy_token.py
pulumiverse_grafana/cloud/get_access_policies.py
pulumiverse_grafana/cloud/get_ips.py
pulumiverse_grafana/cloud/get_organization.py
pulumiverse_grafana/cloud/get_private_data_source_connect_networks.py
pulumiverse_grafana/cloud/get_stack.py
pulumiverse_grafana/cloud/org_member.py
pulumiverse_grafana/cloud/outputs.py
pulumiverse_grafana/cloud/plugin_installation.py
pulumiverse_grafana/cloud/private_data_source_connect_network.py
pulumiverse_grafana/cloud/private_data_source_connect_network_token.py
pulumiverse_grafana/cloud/product_activation_app_o11y_config_v1_alpha1.py
pulumiverse_grafana/cloud/product_activation_k8s_o11y_config_v1_alpha1.py
pulumiverse_grafana/cloud/stack.py
pulumiverse_grafana-2.18.0.dist-info/METADATA
pulumiverse_grafana-2.18.0.dist-info/WHEEL
pulumiverse_grafana-2.18.0.dist-info/top_level.txt
pulumiverse_grafana-2.18.0.dist-info/RECORD
